HISTORY.rst
LICENSE
MANIFEST.in
NOTICE
README.rst
requirements.txt
setup.cfg
setup.py
seleniumpm/__init__.py
seleniumpm/annotations.py
seleniumpm/config.py
seleniumpm/iframe.py
seleniumpm/locator.py
seleniumpm/webpage.py
seleniumpm.egg-info/PKG-INFO
seleniumpm.egg-info/SOURCES.txt
seleniumpm.egg-info/dependency_links.txt
seleniumpm.egg-info/not-zip-safe
seleniumpm.egg-info/requires.txt
seleniumpm.egg-info/top_level.txt
seleniumpm/examples/__init__.py
seleniumpm/examples/google_page.py
seleniumpm/examples/superwikipedia.py
seleniumpm/examples/wikipedia.py
seleniumpm/examples/widgets/WikipediaPersonal.py
seleniumpm/examples/widgets/__init__.py
seleniumpm/webelements/__init__.py
seleniumpm/webelements/button.py
seleniumpm/webelements/checkbox.py
seleniumpm/webelements/clickable.py
seleniumpm/webelements/dropdown.py
seleniumpm/webelements/element.py
seleniumpm/webelements/image.py
seleniumpm/webelements/label.py
seleniumpm/webelements/link.py
seleniumpm/webelements/panel.py
seleniumpm/webelements/radiobutton.py
seleniumpm/webelements/table.py
seleniumpm/webelements/textelement.py
seleniumpm/webelements/textfield.py
seleniumpm/webelements/widget.py