Metadata-Version: 1.1
Name: seleniumpm
Version: 2.11.5
Summary: Selenium Pagemodel implementation for Python.
Home-page: https://github.com/gradeawarrior/python-seleniumpm
Author: Peter Salas
Author-email: selenium-pagemodel@googlegroups.com
License: Apache 2.0
Keywords: testing,seleniumpm,selenium,pagemodel,pageobjectmodel
Platform: UNKNOWN
Classifier: Development Status :: 5 - Production/Stable
Classifier: Intended Audience :: Developers
Classifier: Natural Language :: English
Classifier: License :: OSI Approved :: Apache Software License
Classifier: Programming Language :: Python
Classifier: Programming Language :: Python :: 2.6
Classifier: Programming Language :: Python :: 2.7
Classifier: Programming Language :: Python :: 3
Classifier: Programming Language :: Python :: 3.3
Classifier: Programming Language :: Python :: 3.4
Classifier: Programming Language :: Python :: 3.5
Classifier: Programming Language :: Python :: Implementation :: CPython
Classifier: Programming Language :: Python :: Implementation :: PyPy
